pytest_autocap/__init__.py
pytest_autocap/pluginmodule.py
pytest_autocap-0.0.1.dist-info/LICENSE
pytest_autocap-0.0.1.dist-info/METADATA
pytest_autocap-0.0.1.dist-info/WHEEL
pytest_autocap-0.0.1.dist-info/entry_points.txt
pytest_autocap-0.0.1.dist-info/top_level.txt
pytest_autocap-0.0.1.dist-info/RECORD
