Metadata-Version: 2.1
Name: pytest-autocap
Version: 0.0.1
Summary: automatically capture test & fixture stdout/stderr to files
Home-page: https://github.com/jwdevantier/pytest-autocap
Author: Jesper Wendel Devantier
Author-email: jwd@defmacro.it
License: MIT
Platform: UNKNOWN
Classifier: Framework :: Pytest
License-File: LICENSE
Requires-Dist: pytest (<7.2,>=7.1.2)
